[{"place_id": 155782713, "licence": "Data \u00a9 OpenStreetMap contributors, ODbL 1.0. http://osm.org/copyright", "osm_type": "way", "osm_id": 439003834, "lat": "52.3866352", "lon": "9.723818826716856", "class": "railway", "type": "platform", "place_rank": 30, "importance": 0.11555415588532474, "addresstype": "railway", "name": "Kopernikusstra\u00dfe", "display_name": "Kopernikusstra\u00dfe, Engelbosteler Damm, Nordstadt, North, Hanover, Region Hannover, Lower Saxony, 30167, Germany", "boundingbox": ["52.3862064", "52.3869805", "9.7235931", "9.7240951"]}]